Zpy
execjs
tests
