Metadata-Version: 1.1
Name: zpyshell
Version: 0.1.2.0
Summary: Command line shell with script languages, like python
Home-page: https://albertaleksieiev.github.io/zpy/
Author: Albert Aleksieiev
Author-email: albert.aleksieiev@gmail.com
License: UNKNOWN
Download-URL: https://github.com/albertaleksieiev/zpy/archive/0.1.tar.gz
Keywords: python,command,line,shell,unix,terminal
Platform: UNKNOWN
Classifier: Topic :: Software Development :: Interpreters
Classifier: Development Status :: 2 - Pre-Alpha
Classifier: Environment :: Console
Classifier: License :: OSI Approved :: MIT License
Classifier: Operating System :: Unix
Classifier: Programming Language :: Python
Classifier: Topic :: Terminals
Classifier: Environment :: Console
